{
  "months": {
    "January": {
      "05.01.1993": {
        "firstName": "Alyssa",
        "lastName": "Holland",
        "avatar": "https://randomuser.me/api/portraits/women/51.jpg"
      },
      "25.01.1993": [
        {
          "firstName": "Minnie",
          "lastName": "Myers",
          "avatar": "https://randomuser.me/api/portraits/women/78.jpg"
        },
        {
          "firstName": "Florence",
          "lastName": "Fletcher",
          "avatar": "https://randomuser.me/api/portraits/women/12.jpg"
        }
      ],
      "27.01.1995": {
        "firstName": "Eric",
        "lastName": "Myers",
        "avatar": "https://randomuser.me/api/portraits/women/78.jpg"
      },
      "31.01.2000": {
        "firstName": "Alicia",
        "lastName": "Steward",
        "avatar": "https://randomuser.me/api/portraits/women/5.jpg"
      }
    },
    "February": {
      "05.02.1993": {
        "firstName": "Nathaniel",
        "lastName": "Austin",
        "avatar": "https://randomuser.me/api/portraits/men/15.jpg"
      },
      "12.02.2000": {
        "firstName": "Bryan",
        "lastName": "Fisher",
        "avatar": "https://uinames.com/api/photos/male/12.jpg"
      },
      "20.02.2000": {
        "firstName": "Johnny",
        "lastName": "Schmidt",
        "avatar": "https://uinames.com/api/photos/female/12.jpg"
      },
      "26.02.2000": [
        {
          "firstName": "Michelle",
          "lastName": "Walters",
          "avatar": "https://uinames.com/api/photos/female/1.jpg"
        },
        {
          "firstName": "Janice",
          "lastName": "Sullivan",
          "avatar": "https://uinames.com/api/photos/female/16.jpg"
        },
        {
          "firstName": "Alan",
          "lastName": "Hawkins",
          "avatar": "https://uinames.com/api/photos/male/10.jpg"
        }
      ]
    }
  }
}
